race_result_package_driver_ua-0.0.3.dist-info/licenses/LICENSE
report/__init__.py
report/cli.py
report/driver.py
report/race_result.py
report/report_builder.py
report/utils.py
tests/__init__.py
tests/test_cli.py
race_result_package_driver_ua-0.0.3.dist-info/METADATA
race_result_package_driver_ua-0.0.3.dist-info/WHEEL
race_result_package_driver_ua-0.0.3.dist-info/top_level.txt
race_result_package_driver_ua-0.0.3.dist-info/RECORD
