Metadata-Version: 2.4
Name: Race_result_package_Driver-UA
Version: 0.0.3
Summary: Пакет для відображення результатів гонки
Author-email: Володимир <reggyi10@gmail.com>
License: Copyright (c) 2018 The Python Packaging Authority
Project-URL: Homepage, https://github.com/pypa/sampleproject
Project-URL: Issues, https://github.com/pypa/sampleproject/issues
Classifier: Programming Language :: Python :: 3
Classifier: Operating System :: OS Independent
Requires-Python: >=3.8
License-File: LICENSE
Dynamic: license-file
